pkg_SWR_classTest/__init__.py
pkg_SWR_classTest/pkg_SWR_classTest.py
pkg_SWR_classTest-1.0.1.dist-info/METADATA
pkg_SWR_classTest-1.0.1.dist-info/RECORD
pkg_SWR_classTest-1.0.1.dist-info/WHEEL
pkg_SWR_classTest-1.0.1.dist-info/top_level.txt
