Metadata-Version: 2.1
Name: pkg-SWR-classTest
Version: 1.0.1
Summary: A small example package defining a test class
Home-page: https://github.com/pypa/pkg_SWR_classTest
Author: Sarah Winkler
Author-email: sarah.winkler@initions-consulting.com
License: UNKNOWN
Platform: UNKNOWN
Classifier: Programming Language :: Python :: 3
Classifier: License :: OSI Approved :: MIT License
Classifier: Operating System :: OS Independent
